

# 枚举

## 继承

```java
public final class wx.Season extends java.lang.Enum<wx.Season> {
  public static final wx.Season Spring;
  public static final wx.Season Summer;
  private static final wx.Season[] $VALUES;
  public static wx.Season[] values();
  public static wx.Season valueOf(java.lang.String);
  private wx.Season();
  static {};
}
```

在static{}里生成常量，并且赋值到类对象数组里面。

通过Javap  -c -p 反编译查看。继承自java.lang.Enum<Season>,会自动添加 private static final Season[] $VALUES;

```java
public final class Season extends java.lang.Enum<Season> {
  public static final Season Spring;

  public static final Season Summer;

  public static final Season Autumn;

  public static final Season Winter;

  private static final Season[] $VALUES;

  public static Season[] values();
    Code:
       0: getstatic     #1                  // Field $VALUES:[LSeason;
       3: invokevirtual #2                  // Method "[LSeason;".clone:()Ljava/lang/Object;
       6: checkcast     #3                  // class "[LSeason;"
       9: areturn

  public static Season valueOf(java.lang.String);
    Code:
       0: ldc           #4                  // class Season
       2: aload_0
       3: invokestatic  #5                  // Method java/lang/Enum.valueOf:(Ljava/lang/Class;Ljava/lang/String;)Ljava/lang/Enum;
       6: checkcast     #4                  // class Season
       9: areturn

  private Season();
    Code:
       0: aload_0
       1: aload_1
       2: iload_2
       3: invokespecial #6                  // Method java/lang/Enum."<init>":(Ljava/lang/String;I)V
       6: return

  static {};
    Code:
       0: new           #4                  // class Season
       3: dup
       4: ldc           #7                  // String Spring
       6: iconst_0
       7: invokespecial #8                  // Method "<init>":(Ljava/lang/String;I)V
      10: putstatic     #9                  // Field Spring:LSeason;
      13: new           #4                  // class Season
      16: dup
      17: ldc           #10                 // String Summer
      19: iconst_1
      20: invokespecial #8                  // Method "<init>":(Ljava/lang/String;I)V
      23: putstatic     #11                 // Field Summer:LSeason;
      26: new           #4                  // class Season
      29: dup
      30: ldc           #12                 // String Autumn
      32: iconst_2
      33: invokespecial #8                  // Method "<init>":(Ljava/lang/String;I)V
      36: putstatic     #13                 // Field Autumn:LSeason;
      39: new           #4                  // class Season
      42: dup
      43: ldc           #14                 // String Winter
      45: iconst_3
      46: invokespecial #8                  // Method "<init>":(Ljava/lang/String;I)V
      49: putstatic     #15                 // Field Winter:LSeason;
      52: iconst_4
      53: anewarray     #4                  // class Season
      56: dup
      57: iconst_0
      58: getstatic     #9                  // Field Spring:LSeason;
      61: aastore
      62: dup
      63: iconst_1
      64: getstatic     #11                 // Field Summer:LSeason;
      67: aastore
      68: dup
      69: iconst_2
      70: getstatic     #13                 // Field Autumn:LSeason;
      73: aastore
      74: dup
      75: iconst_3
      76: getstatic     #15                 // Field Winter:LSeason;
      79: aastorec
      80: putstatic     #1                  // Field $VALUES:[LSeason;
      83: return
}
```

## 搭配switch

通过.ordinal()来获得数组下标。

然后在    比对数组下标跳转lookupswitch  { // 1
                     1: 40
               default: 51
          }

```java
public enum Season {
    Spring,
    Summer;

    private Season() {
    }
}
public static void main(String[] args) {
        System.out.println("HELLo");
        Season s = Season.Spring;
        switch(s) {
        case Spring:
            System.out.println("春天");
            break;
        default:
            System.out.println("else");
        }

    }
```

反编译之后：

```java
 public static void main(java.lang.String[]);
    Code:
       0: getstatic     #2                  // Field java/lang/System.out:Ljava/io/PrintStream;
       3: ldc           #3                  // String HELLo
       5: invokevirtual #4                  // Method java/io/PrintStream.println:(Ljava/lang/String;)V
       8: getstatic     #5                  // Field wx/Season.Spring:Lwx/Season;
      11: astore_1
      12: getstatic     #6                  // Field Main$1.$SwitchMap$wx$Season:[I
      15: aload_1
      16: invokevirtual #7                  // Method wx/Season.ordinal:()I
      19: iaload
      20: lookupswitch  { // 1
                     1: 40
               default: 51
          }
      40: getstatic     #2                  // Field java/lang/System.out:Ljava/io/PrintStream;
      43: ldc           #8                  // String 春天
      45: invokevirtual #4                  // Method java/io/PrintStream.println:(Ljava/lang/String;)V
      48: goto          59
      51: getstatic     #2                  // Field java/lang/System.out:Ljava/io/PrintStream;
      54: ldc           #9                  // String else
      56: invokevirtual #4                  // Method java/io/PrintStream.println:(Ljava/lang/String;)V
      59: return
}
```

## 单例

### 序列化（Enum类实现）

#### 序列化

ObjectOutputStream。writeEnum（）,会把对象名序列化。

```java
private void writeEnum(Enum<?> en,
                           ObjectStreamClass desc,
                           boolean unshared)
        throws IOException
    {
        bout.writeByte(TC_ENUM);
        ObjectStreamClass sdesc = desc.getSuperDesc();
        writeClassDesc((sdesc.forClass() == Enum.class) ? desc : sdesc, false);
        handles.assign(unshared ? null : en);
        writeString(en.name(), false);
    }
```



#### 反序列化1

```java
    private void readObject(ObjectInputStream in) throws IOException,
        ClassNotFoundException {
        throw new InvalidObjectException("can't deserialize enum");
    }
```

#### 反序列化2

关键的代码就是在readObject()里的readObject0()实现的

readObject0()对类的实现体现在switch选择器上：

ObjectInputStream.readObject0()

```java
                case TC_ENUM:
                    if (type == String.class) {
                        throw new ClassCastException("Cannot cast an enum to java.lang.String");
                    }
                    return checkResolve(readEnum(unshared));
```

根据名字从枚举数组获取枚举对象；

```java
rivate Enum<?> readEnum(boolean unshared) throws IOException {
        if (bin.readByte() != TC_ENUM) {
            throw new InternalError();
        }

        ObjectStreamClass desc = readClassDesc(false);
        if (!desc.isEnum()) {
            throw new InvalidClassException("non-enum class: " + desc);
        }

        int enumHandle = handles.assign(unshared ? unsharedMarker : null);
        ClassNotFoundException resolveEx = desc.getResolveException();
        if (resolveEx != null) {
            handles.markException(enumHandle, resolveEx);
        }

        String name = readString(false);
        Enum<?> result = null;
        Class<?> cl = desc.forClass();
        if (cl != null) {
            try {
                @SuppressWarnings("unchecked")
                Enum<?> en = Enum.valueOf((Class)cl, name);
                result = en;
            } catch (IllegalArgumentException ex) {
                throw (IOException) new InvalidObjectException(
                    "enum constant " + name + " does not exist in " +
                    cl).initCause(ex);
            }
            if (!unshared) {
                handles.setObject(enumHandle, result);
            }
        }

        handles.finish(enumHandle);
        passHandle = enumHandle;
        return result;
    }
```

### 初始化及线程安全

  <clinit>()  方法是由编译器自动收集类中的所有类变量（static）的赋值动作和静态语句块（static{}）块中的语句合并产生的。因此， private   static  Singleton  singleton  =  new  Singleton(); 也会被放入到这个方法中。

    虚拟机会保证一个类的 <clinit>() 方法在多线程环境中被正确的加锁、同步，如果多个线程同时去初始化一个类，那么只会有一个线程去执行这个类的 <clinit>() 方法，其他线程都需要阻塞等待，直到活动线程执行 <clinit>() 方法完毕。需要注意的是，其他线程虽然会被阻塞，但如果执行 <clinit>() 方法的那条线程退出 <clinit>() 方法后，其他线程唤醒后不会再次进入 <clinit>() 方法。同一个类加载器下，一个类型只会初始化一次。

static{}即cinit()方法。 反编译得知枚举类在static{}里生成常量，并且赋值到类对象数组里面。保证枚举类是线程安全的单例。

### 反射

不允许对枚举的构造器使用反射调用。查constructor.newInstance源码，就可以看到，有个专门针对枚举的`if`判断。

```java
public T newInstance(Object ... initargs) throws InstantiationException, IllegalAccessException,IllegalArgumentException, InvocationTargetException {
    if (!override) {
        if (!Reflection.quickCheckMemberAccess(clazz, modifiers)) {
            Class<?> caller = Reflection.getCallerClass();
            checkAccess(caller, clazz, null, modifiers);
        }
    }
    //判断是否是枚举，如果是枚举的话，报、抛出异常
    if ((clazz.getModifiers() & Modifier.ENUM) != 0)
        //抛出异常，不能通过反射创建枚举
        throw new IllegalArgumentException("Cannot reflectively create enum objects");
    ConstructorAccessor ca = constructorAccessor;   // read volatile
    if (ca == null) {
        ca = acquireConstructorAccessor();
    }
    @SuppressWarnings("unchecked")
    T inst = (T) ca.newInstance(initargs);
    return inst;
}
```

### 克隆

Enum<T>类

```java
protected final Object clone() throws CloneNotSupportedException {
    throw new CloneNotSupportedException();
}
```

## 比较

比较的是ordinal,即声明顺序。

```java
    public final int compareTo(E o) {
        Enum<?> other = (Enum<?>)o;
        Enum<E> self = this;
        if (self.getClass() != other.getClass() && // optimization
            self.getDeclaringClass() != other.getDeclaringClass())
            throw new ClassCastException();
        return self.ordinal - other.ordinal;
    }
```

